opencensus/__init__.py
opencensus/ext/__init__.py
opencensus/ext/datadog/__init__.py
opencensus/ext/datadog/traces.py
opencensus/ext/datadog/transport.py
opencensus_ext_datadog-0.1.0.dist-info/METADATA
opencensus_ext_datadog-0.1.0.dist-info/WHEEL
opencensus_ext_datadog-0.1.0.dist-info/namespace_packages.txt
opencensus_ext_datadog-0.1.0.dist-info/top_level.txt
opencensus_ext_datadog-0.1.0.dist-info/RECORD
